gnani_voicebiometric_api/__init__.py
gnani_voicebiometric_api/authenticate.py
gnani_voicebiometric_api/disenroll.py
gnani_voicebiometric_api/enroll.py
gnani_voicebiometric_api/log_config/__init__.py
gnani_voicebiometric_api/log_config/logger.py
gnani_voicebiometric_api/utils/__init__.py
gnani_voicebiometric_api-0.0.1.dist-info/DESCRIPTION.rst
gnani_voicebiometric_api-0.0.1.dist-info/METADATA
gnani_voicebiometric_api-0.0.1.dist-info/RECORD
gnani_voicebiometric_api-0.0.1.dist-info/WHEEL
gnani_voicebiometric_api-0.0.1.dist-info/metadata.json
gnani_voicebiometric_api-0.0.1.dist-info/top_level.txt
